messageformat2/__init__.py
messageformat2/builtins.py
messageformat2/cli.py
messageformat2/datamodel.py
messageformat2/errors.py
messageformat2/message.py
messageformat2/parser.py
messageformat2/runtime.py
messageformat2-0.1.1.dist-info/METADATA
messageformat2-0.1.1.dist-info/WHEEL
messageformat2-0.1.1.dist-info/entry_points.txt
messageformat2-0.1.1.dist-info/licenses/LICENSE
messageformat2-0.1.1.dist-info/RECORD
