Metadata-Version: 2.4
Name: messageformat2
Version: 0.1.1
Summary: Python implementation of Unicode MessageFormat 2.0
Project-URL: Homepage, https://github.com/tomasr8/messageformat2
Project-URL: Github, https://github.com/tomasr8/messageformat2
Author-email: Tomas Roun <tomas.roun8@gmail.com>
License: MIT License
License-File: LICENSE
Keywords: cldr,gettext,i18n,internationalization,localization,messageformat,messageformat 2
Classifier: License :: OSI Approved :: MIT License
Classifier: Operating System :: OS Independent
Classifier: Programming Language :: Python :: 3
Classifier: Programming Language :: Python :: 3.12
Classifier: Topic :: Scientific/Engineering
Classifier: Topic :: Software Development :: Internationalization
Classifier: Topic :: Software Development :: Localization
Requires-Python: >=3.12
Requires-Dist: babel==2.17.0
Requires-Dist: click==8.3.1
